terra_colab/__init__.py
terra_colab/commands.py
terra_colab/project.py
terra_colab-1.1.dist-info/METADATA
terra_colab-1.1.dist-info/WHEEL
terra_colab-1.1.dist-info/entry_points.txt
terra_colab-1.1.dist-info/top_level.txt
terra_colab-1.1.dist-info/RECORD
