Metadata-Version: 2.1
Name: terra-colab
Version: 1.1
Summary: UNKNOWN
Home-page: UNKNOWN
License: UNKNOWN
Platform: UNKNOWN
Requires-Dist: requests (~=2.23.0)
Requires-Dist: GitPython (==3.1.18)
Requires-Dist: python-dotenv (==0.19.0)
Requires-Dist: tensorflow (==2.6.0)
Requires-Dist: Django (==3.2.6)
